{
  "model": "app.models.aisles.Aisle",
  "data": [
    {
      "!module_id": {
        "model": "app.models.modules.Module",
        "filter": {
          "module_number": "CSR2A"
        }
      },
      "aisle_number": 21
    },
    {
      "!module_id": {
        "model": "app.models.modules.Module",
        "filter": {
          "module_number": "CSR2A"
        }
      },
      "aisle_number": 22
    },
    {
      "!module_id": {
        "model": "app.models.modules.Module",
        "filter": {
          "module_number": "CSR2A"
        }
      },
      "aisle_number": 23
    },
    {
      "!module_id": {
        "model": "app.models.modules.Module",
        "filter": {
          "module_number": "CSR2A"
        }
      },
      "aisle_number": 24
    },
    {
      "!module_id": {
        "model": "app.models.modules.Module",
        "filter": {
          "module_number": "CSR2A"
        }
      },
      "aisle_number": 25
    },
    {
      "!module_id": {
        "model": "app.models.modules.Module",
        "filter": {
          "module_number": "CSR2A"
        }
      },
      "aisle_number": 26
    },
    {
      "!module_id": {
        "model": "app.models.modules.Module",
        "filter": {
          "module_number": "CSR2A"
        }
      },
      "aisle_number": 27
    },
    {
      "!module_id": {
        "model": "app.models.modules.Module",
        "filter": {
          "module_number": "CSR2A"
        }
      },
      "aisle_number": 28
    }
  ]
}