{
  "model": "app.models.aisles.Aisle",
  "data": [
    {
      "!module_id": {
        "model": "app.models.modules.Module",
        "filter": {
          "module_number": "CSR1"
        }
      },
      "!aisle_number_id": {
        "model": "app.models.aisle_numbers.AisleNumber",
        "filter": {
          "number": 45
        }
      }
    },
    {
      "!module_id": {
        "model": "app.models.modules.Module",
        "filter": {
          "module_number": "CSR1"
        }
      },
      "!aisle_number_id": {
        "model": "app.models.aisle_numbers.AisleNumber",
        "filter": {
          "number": 46
        }
      }
    },
    {
      "!module_id": {
        "model": "app.models.modules.Module",
        "filter": {
          "module_number": "CSR1"
        }
      },
      "!aisle_number_id": {
        "model": "app.models.aisle_numbers.AisleNumber",
        "filter": {
          "number": 47
        }
      }
    },
    {
      "!module_id": {
        "model": "app.models.modules.Module",
        "filter": {
          "module_number": "CSR1"
        }
      },
      "!aisle_number_id": {
        "model": "app.models.aisle_numbers.AisleNumber",
        "filter": {
          "number": 48
        }
      }
    },
    {
      "!module_id": {
        "model": "app.models.modules.Module",
        "filter": {
          "module_number": "CSR1"
        }
      },
      "!aisle_number_id": {
        "model": "app.models.aisle_numbers.AisleNumber",
        "filter": {
          "number": 49
        }
      }
    },
    {
      "!module_id": {
        "model": "app.models.modules.Module",
        "filter": {
          "module_number": "CSR1"
        }
      },
      "!aisle_number_id": {
        "model": "app.models.aisle_numbers.AisleNumber",
        "filter": {
          "number": 50
        }
      }
    },
    {
      "!module_id": {
        "model": "app.models.modules.Module",
        "filter": {
          "module_number": "CSR1"
        }
      },
      "!aisle_number_id": {
        "model": "app.models.aisle_numbers.AisleNumber",
        "filter": {
          "number": 51
        }
      }
    }
  ]
}
